G6_face_recognition/__init__.py
G6_face_recognition/encode_face_model.py
G6_face_recognition/face_matching.py
G6_face_recognition/feature_encode.py
G6_face_recognition/main.py
G6_face_recognition-0.0.2.dist-info/LICENSE
G6_face_recognition-0.0.2.dist-info/METADATA
G6_face_recognition-0.0.2.dist-info/WHEEL
G6_face_recognition-0.0.2.dist-info/entry_points.txt
G6_face_recognition-0.0.2.dist-info/top_level.txt
G6_face_recognition-0.0.2.dist-info/RECORD
