Metadata-Version: 2.1
Name: G6-face-recognition
Version: 0.0.2
Summary: A Python package to face recognition.
Home-page: UNKNOWN
Author: Gate6
Author-email: rajendra.khabiya@gate6.com
License: MIT
Project-URL: Source, https://github.com/gate6/iris-recognition-sample-code/tree/face-recognition
Platform: UNKNOWN
Classifier: License :: OSI Approved :: MIT License
Classifier: Natural Language :: English
Classifier: Programming Language :: Python
Classifier: Programming Language :: Python :: 2.7
Classifier: Programming Language :: Python :: 3.4
Classifier: Programming Language :: Python :: 3.5
Classifier: Programming Language :: Python :: 3
Requires-Dist: opencv-contrib-python
Requires-Dist: scikit-image
Requires-Dist: scipy
Requires-Dist: numpy
Requires-Dist: matplotlib
Requires-Dist: imutils
